beautiful_validator-0.0.2.dist-info/licenses/LICENSE
pydefender/__init__.py
pydefender/config.py
pydefender/decorators.py
pydefender/exceptions.py
pydefender/utils.py
pydefender/ai/__init__.py
pydefender/ai/auto_correction.py
pydefender/ai/intent_recognition.py
pydefender/ai/learning_engine.py
pydefender/ai/pattern_detection.py
pydefender/ai/smart_validation.py
pydefender/converters/__init__.py
pydefender/converters/base.py
pydefender/converters/currency_converters.py
pydefender/converters/date_converters.py
pydefender/converters/encoding_converters.py
pydefender/converters/format_converters.py
pydefender/converters/number_converters.py
pydefender/converters/string_converters.py
pydefender/extras/__init__.py
pydefender/extras/data_generators.py
pydefender/extras/export_validators.py
pydefender/extras/migration_tools.py
pydefender/extras/plugin_system.py
pydefender/extras/schema_builder.py
pydefender/integrations/__init__.py
pydefender/integrations/django_integration.py
pydefender/integrations/fastapi_integration.py
pydefender/integrations/flask_integration.py
pydefender/integrations/marshmallow_integration.py
pydefender/integrations/pandas_integration.py
pydefender/integrations/pydantic_integration.py
pydefender/integrations/sqlalchemy_integration.py
pydefender/localization/__init__.py
pydefender/localization/custom.py
pydefender/localization/de.py
pydefender/localization/en.py
pydefender/localization/es.py
pydefender/localization/fr.py
pydefender/localization/manager.py
pydefender/localization/ru.py
pydefender/localization/zh.py
pydefender/monitoring/__init__.py
pydefender/monitoring/error_tracker.py
pydefender/monitoring/performance_monitor.py
pydefender/monitoring/stats_collector.py
pydefender/monitoring/usage_analytics.py
pydefender/performance/__init__.py
pydefender/performance/async_validation.py
pydefender/performance/batch_processing.py
pydefender/performance/caching.py
pydefender/performance/lazy_loading.py
pydefender/presets/__init__.py
pydefender/presets/advanced.py
pydefender/presets/banking.py
beautiful_validator-0.0.2.dist-info/METADATA
beautiful_validator-0.0.2.dist-info/WHEEL
beautiful_validator-0.0.2.dist-info/top_level.txt
beautiful_validator-0.0.2.dist-info/RECORD
