Metadata-Version: 2.4
Name: beautiful-validator
Version: 0.0.2
Summary: 🛡️ Beautiful Smart Input Validation for Python
Home-page: https://github.com/pydefender/pydefender
Author: PyDefender Team
Author-email: team@pydefender.dev
License: MIT
Project-URL: Homepage, https://github.com/pydefender/pydefender
Project-URL: Bug Reports, https://github.com/pydefender/pydefender/issues
Project-URL: Source, https://github.com/pydefender/pydefender
Project-URL: Documentation, https://pydefender.dev/docs
Project-URL: Changelog, https://github.com/pydefender/pydefender/blob/main/CHANGELOG.md
Keywords: validation,input,data,forms,decorators,beautiful,smart,defensive,programming,python,validators,validation-library,input-validation,data-validation,form-validation,type-checking
Platform: any
Classifier: Development Status :: 2 - Pre-Alpha
Classifier: Intended Audience :: Developers
Classifier: Topic :: Software Development :: Libraries :: Python Modules
Classifier: Topic :: Software Development :: Quality Assurance
Classifier: License :: OSI Approved :: MIT License
Classifier: Programming Language :: Python :: 3
Classifier: Programming Language :: Python :: 3.8
Classifier: Programming Language :: Python :: 3.9
Classifier: Programming Language :: Python :: 3.10
Classifier: Programming Language :: Python :: 3.11
Classifier: Programming Language :: Python :: 3.12
Classifier: Operating System :: OS Independent
Classifier: Typing :: Typed
Requires-Python: >=3.8
License-File: LICENSE
Requires-Dist: colorama>=0.4.6
Provides-Extra: dev
Requires-Dist: pytest>=7.4.0; extra == "dev"
Requires-Dist: black>=23.0.0; extra == "dev"
Requires-Dist: isort>=5.12.0; extra == "dev"
Requires-Dist: mypy>=1.5.0; extra == "dev"
Requires-Dist: pre-commit>=3.0.0; extra == "dev"
Provides-Extra: test
Requires-Dist: pytest>=7.4.0; extra == "test"
Requires-Dist: pytest-cov>=4.1.0; extra == "test"
Requires-Dist: coverage>=7.0.0; extra == "test"
Provides-Extra: docs
Requires-Dist: mkdocs>=1.5.0; extra == "docs"
Requires-Dist: mkdocs-material>=9.0.0; extra == "docs"
Requires-Dist: mkdocstrings>=0.22.0; extra == "docs"
Dynamic: author
Dynamic: author-email
Dynamic: classifier
Dynamic: description
Dynamic: description-content-type
Dynamic: home-page
Dynamic: keywords
Dynamic: license
Dynamic: license-file
Dynamic: platform
Dynamic: project-url
Dynamic: provides-extra
Dynamic: requires-dist
Dynamic: requires-python
Dynamic: summary
